chaosplt_relational_storage/__init__.py
chaosplt_relational_storage/db.py
chaosplatform_relational_storage-0.2.2.dist-info/LICENSE
chaosplatform_relational_storage-0.2.2.dist-info/METADATA
chaosplatform_relational_storage-0.2.2.dist-info/WHEEL
chaosplatform_relational_storage-0.2.2.dist-info/top_level.txt
chaosplatform_relational_storage-0.2.2.dist-info/RECORD
