Metadata-Version: 2.1
Name: chaosplatform-relational-storage
Version: 0.2.2
Summary: A library for relational database access from the Chaos Platform
Home-page: https://github.com/chaostoolkit/chaosplatform-relational-storage
Author: ChaosIQ
Author-email: contact@chaosiq.io
License: Apache Software License 2.0
Project-URL: CI: Travis, https://travis-ci.org/chaostoolkit/chaosplatform-relational-storage
Project-URL: Docs: RTD, https://docs.chaosplatform.org
Project-URL: GitHub: issues, https://chaostoolkit/chaostoolkit/chaosplatform-relational-storage/issues
Project-URL: GitHub: repo, https://chaostoolkit/chaostoolkit/chaosplatform-relational-storage
Platform: UNKNOWN
Classifier: Development Status :: 5 - Production/Stable
Classifier: Intended Audience :: Developers
Classifier: License :: OSI Approved :: Apache Software License
Classifier: Operating System :: Unix
Classifier: Operating System :: POSIX
Classifier: Programming Language :: Python
Classifier: Programming Language :: Python :: 3
Classifier: Programming Language :: Python :: 3.6
Classifier: Programming Language :: Python :: 3.7
Classifier: Programming Language :: Python :: Implementation :: CPython
Classifier: Topic :: Utilities
Requires-Python: >=3.6.*
Requires-Dist: sqlalchemy (>=1.2.15)
Requires-Dist: sqlalchemy-utils (>=0.33.9)
Requires-Dist: sqlalchemy-json (>=0.2.1)
Requires-Dist: attrs (>=18.2.0)
